docker_tunnel.py
docker_tunnel-0.1.2.dist-info/DESCRIPTION.rst
docker_tunnel-0.1.2.dist-info/entry_points.txt
docker_tunnel-0.1.2.dist-info/METADATA
docker_tunnel-0.1.2.dist-info/metadata.json
docker_tunnel-0.1.2.dist-info/RECORD
docker_tunnel-0.1.2.dist-info/top_level.txt
docker_tunnel-0.1.2.dist-info/WHEEL
