Metadata-Version: 2.0
Name: docker-tunnel
Version: 0.1.2
Summary: Using remote docker with SSH tunnel.
Home-page: https://github.com/tonyseek/docker-tunnel
Author: Jiangge Zhang
Author-email: tonyseek@gmail.com
License: MIT
Platform: Linux
Platform: Mac
Classifier: Development Status :: 3 - Alpha
Classifier: Environment :: Console
Classifier: Intended Audience :: Developers
Classifier: Intended Audience :: System Administrators
Classifier: License :: OSI Approved :: MIT License
Classifier: Operating System :: MacOS
Classifier: Operating System :: POSIX
Classifier: Programming Language :: Python
Classifier: Programming Language :: Python :: 2.7
Classifier: Programming Language :: Python :: 3.3
Classifier: Programming Language :: Python :: 3.4
Classifier: Topic :: Utilities
Requires-Dist: click
